userdefinedfields/README.md
userdefinedfields/__init__.py
userdefinedfields/admin.py
userdefinedfields/context_processors.py
userdefinedfields/factories.py
userdefinedfields/fields.py
userdefinedfields/forms.py
userdefinedfields/migrations/0001_initial.py
userdefinedfields/migrations/0002_auto_20200923_0122.py
userdefinedfields/migrations/0003_auto_20201120_0209.py
userdefinedfields/migrations/0004_alter_extrafield_widget.py
userdefinedfields/migrations/__init__.py
userdefinedfields/models.py
userdefinedfields/widgets.py
django_user_defined_fields-0.0.23.dist-info/LICENSE
django_user_defined_fields-0.0.23.dist-info/METADATA
django_user_defined_fields-0.0.23.dist-info/WHEEL
django_user_defined_fields-0.0.23.dist-info/RECORD
