Metadata-Version: 2.3
Name: django-user-defined-fields
Version: 0.0.23
Summary: A Django app for user defined fields
License: MIT
Keywords: django,custom,fields,json
Author: Aidan Lister
Author-email: aidan@uptickhq.com
Requires-Python: >=3.7,<4
Classifier: Environment :: Web Environment
Classifier: Framework :: Django
Classifier: Intended Audience :: Developers
Classifier: License :: OSI Approved :: BSD License
Classifier: License :: OSI Approved :: MIT License
Classifier: Operating System :: OS Independent
Classifier: Programming Language :: Python
Classifier: Programming Language :: Python :: 3
Classifier: Programming Language :: Python :: 3.7
Classifier: Programming Language :: Python :: 3.8
Classifier: Programming Language :: Python :: 3.9
Classifier: Programming Language :: Python :: 3.10
Classifier: Programming Language :: Python :: 3.11
Classifier: Programming Language :: Python :: 3.12
Classifier: Programming Language :: Python :: 3.13
Classifier: Programming Language :: Python :: 3 :: Only
Classifier: Programming Language :: Python :: 3.6
Classifier: Topic :: Internet :: WWW/HTTP
Classifier: Topic :: Internet :: WWW/HTTP :: Dynamic Content
Requires-Dist: Django (>=2.2.24)
Project-URL: Homepage, https://github.com/uptick/django-user-defined-fields/
Project-URL: Repository, https://github.com/uptick/django-user-defined-fields/
